libname/__init__.py
libname/port_scanner.py
port_scann-0.1.1.dist-info/LICENSE
port_scann-0.1.1.dist-info/METADATA
port_scann-0.1.1.dist-info/WHEEL
port_scann-0.1.1.dist-info/top_level.txt
port_scann-0.1.1.dist-info/RECORD
