Metadata-Version: 2.1
Name: port-scann
Version: 0.1.1
Summary: Port Scanner
Home-page: UNKNOWN
Author: CyberCommands
License: UNKNOWN
Keywords: python,port,scan,port scanner,port scan,TCP scan
Platform: UNKNOWN
Classifier: Development Status :: 1 - Planning
Classifier: Intended Audience :: Developers
Classifier: Programming Language :: Python :: 3
Classifier: Operating System :: Unix
Classifier: Operating System :: MacOS :: MacOS X
Classifier: Operating System :: Microsoft :: Windows
Requires-Dist: colorama
Requires-Dist: argparse
